sqlalchemy_libsql/__init__.py
sqlalchemy_libsql/aiolibsql.py
sqlalchemy_libsql/libsql.py
sqlalchemy_libsql-0.2.0rc1.dist-info/LICENSE.md
sqlalchemy_libsql-0.2.0rc1.dist-info/METADATA
sqlalchemy_libsql-0.2.0rc1.dist-info/WHEEL
sqlalchemy_libsql-0.2.0rc1.dist-info/entry_points.txt
sqlalchemy_libsql-0.2.0rc1.dist-info/RECORD
